{
  "周一": {
    "直接访问": 320,
    "邮件营销": 120,
    "联盟广告": 220,
    "视频广告": 150,
    "搜索引擎": 862,
    "百度": 620,
    "谷歌": 120,
    "必应": 60,
    "其他": 62
  },
  "周二": {
    "直接访问": 332,
    "邮件营销": 132,
    "联盟广告": 182,
    "视频广告": 232,
    "搜索引擎": 1018,
    "百度": 732,
    "谷歌": 132,
    "必应": 72,
    "其他": 82
  },
  "周三": {
    "直接访问": 301,
    "邮件营销": 101,
    "联盟广告": 191,
    "视频广告": 201,
    "搜索引擎": 964,
    "百度": 701,
    "谷歌": 101,
    "必应": 71,
    "其他": 91
  },
  "周四": {
    "直接访问": 334,
    "邮件营销": 134,
    "联盟广告": 234,
    "视频广告": 154,
    "搜索引擎": 1026,
    "百度": 734,
    "谷歌": 134,
    "必应": 74,
    "其他": 84
  },
  "周五": {
    "直接访问": 390,
    "邮件营销": 90,
    "联盟广告": 290,
    "视频广告": 190,
    "搜索引擎": 1679,
    "百度": 1090,
    "谷歌": 290,
    "必应": 190,
    "其他": 109
  },
  "周六": {
    "直接访问": 330,
    "邮件营销": 230,
    "联盟广告": 330,
    "视频广告": 330,
    "搜索引擎": 1600,
    "百度": 1130,
    "谷歌": 230,
    "必应": 130,
    "其他": 110
  },
  "周日": {
    "直接访问": 320,
    "邮件营销": 210,
    "联盟广告": 310,
    "视频广告": 410,
    "搜索引擎": 1570,
    "百度": 1120,
    "谷歌": 220,
    "必应": 110,
    "其他": 120
  }
}